Metadata-Version: 2.1
Name: PyHamcrest
Version: 2.0.3
Summary: Hamcrest framework for matcher objects
Home-page: https://github.com/hamcrest/PyHamcrest
Author: Chris Rose
Author-email: offline@offby1.net
License: New BSD
Download-URL: http://pypi.python.org/packages/source/P/PyHamcrest/PyHamcrest-2.0.3.tar.gz
Keywords: hamcrest matchers pyunit unit test testing unittest unittesting
Platform: All
Classifier: Development Status :: 5 - Production/Stable
Classifier: Environment :: Console
Classifier: Intended Audience :: Developers
Classifier: License :: OSI Approved :: BSD License
Classifier: Natural Language :: English
Classifier: Operating System :: OS Independent
Classifier: Programming Language :: Python :: 3
Classifier: Programming Language :: Python :: 3.6
Classifier: Programming Language :: Python :: 3.7
Classifier: Programming Language :: Python :: 3.8
Classifier: Programming Language :: Python :: Implementation :: CPython
Classifier: Programming Language :: Python :: Implementation :: Jython
Classifier: Programming Language :: Python :: Implementation :: PyPy
Classifier: Topic :: Software Development
Classifier: Topic :: Software Development :: Quality Assurance
Classifier: Topic :: Software Development :: Testing
Provides: hamcrest
Requires-Python: >=3.5
Provides-Extra: docs
Provides-Extra: tests
Provides-Extra: tests-numpy
Provides-Extra: dev
License-File: LICENSE.txt
